uv_dynamic_versioning/__init__.py
uv_dynamic_versioning/base.py
uv_dynamic_versioning/cli.py
uv_dynamic_versioning/hooks.py
uv_dynamic_versioning/main.py
uv_dynamic_versioning/metadata_hook.py
uv_dynamic_versioning/schemas.py
uv_dynamic_versioning/template.py
uv_dynamic_versioning/version_source.py
uv_dynamic_versioning-0.13.0.dist-info/METADATA
uv_dynamic_versioning-0.13.0.dist-info/WHEEL
uv_dynamic_versioning-0.13.0.dist-info/entry_points.txt
uv_dynamic_versioning-0.13.0.dist-info/licenses/LICENSE
uv_dynamic_versioning-0.13.0.dist-info/RECORD
